watchdogdev.cpython-37m-x86_64-linux-gnu.so
watchdogdev-1.0.0.dist-info/METADATA
watchdogdev-1.0.0.dist-info/RECORD
watchdogdev-1.0.0.dist-info/WHEEL
watchdogdev-1.0.0.dist-info/top_level.txt
